{
  "4aaaa3a1-e29d-4578-a830-55945eb21eba": {
    "processed_at": "2026-03-19T10:50:29+00:00",
    "processed_messages": 2
  },
  "58ae53ad-38f7-486e-ab01-721e03a81f3b": {
    "processed_at": "2026-03-19T10:50:29+00:00",
    "processed_messages": 2
  },
  "93987a3f-3db6-4cc4-ba99-2a506eb6ed06": {
    "processed_at": "2026-03-19T10:50:29+00:00",
    "processed_messages": 2
  },
  "523bd701-d0c0-4ccf-874c-5753ab909a24": {
    "processed_at": "2026-03-19T10:50:29+00:00",
    "processed_messages": 2
  }
}
